[
  {
    "boardName": "conference-call",
    "items":  [
      {
        "color": "#000000",
        "id": "78f61f62-d291-4853-a7a2-390810f1e5f5",
        "points": [
          {"x": 140, "y": 123.85415649414062},
          {"x": 141, "y": 123.85415649414062},
          {"x": 152, "y": 123.85415649414062},
          {"x": 168, "y": 123.85415649414062},
          {"x": 191, "y": 123.85415649414062},
          {"x": 213, "y": 125.85415649414062}
        ],
        "tool": "pencil",
        "client_id": "fefb0d04-105b-4bbd-9891-339c30e1eb5b"
      },
      {
        "color": "#000000",
        "id": "78f61f62-d291-4853-a7a2-390810f1e5f5",
        "points": [
          {"x": 140, "y": 131.85415649414062},
          {"x": 141, "y": 131.85415649414062},
          {"x": 152, "y": 131.85415649414062},
          {"x": 168, "y": 131.85415649414062},
          {"x": 191, "y": 131.85415649414062},
          {"x": 213, "y": 133.85415649414062}
        ],
        "tool": "pencil",
        "connection_id": "fefb0d04-105b-4bbd-9891-339c30e1eb5b"
      }
    ]
  },
  {
    "boardName": "chem-class",
    "items":  [
      {
        "color": "#000000",
        "id": "78f61f62-d291-4853-a7a2-390810f1e5f5",
        "points": [
          {"x": 140, "y": 171.85415649414062},
          {"x": 141, "y": 171.85415649414062},
          {"x": 152, "y": 171.85415649414062},
          {"x": 168, "y": 171.85415649414062},
          {"x": 191, "y": 171.85415649414062},
          {"x": 213, "y": 171.85415649414062}
        ],
        "tool": "pencil",
        "client_id": "cfb518ab-33c0-4364-99b3-adcfeea7cd03"
      }
    ]
  }
]


